ros_web_gui/__init__.py
ros_web_gui/__main__.py
ros_web_gui/app.py
ros_web_gui/config.yaml
ros_web_gui/menu.py
ros_web_gui/node.py
ros_web_gui/param.py
ros_web_gui/ros.py
ros_web_gui/service.py
ros_web_gui/topic.py
ros_web_gui/util.py
ros_web_gui/static/jquery.js
ros_web_gui/templates/base.html
ros_web_gui/templates/base_with_list.html
ros_web_gui/templates/base_with_svg.html
ros_web_gui/templates/service.html
ros_web_gui/templates/topic.html
ros_web_gui-0.2.6.data/scripts/ros_web_gui
ros_web_gui-0.2.6.dist-info/LICENSE
ros_web_gui-0.2.6.dist-info/METADATA
ros_web_gui-0.2.6.dist-info/WHEEL
ros_web_gui-0.2.6.dist-info/top_level.txt
ros_web_gui-0.2.6.dist-info/RECORD
