Metadata-Version: 2.1
Name: ros-web-gui
Version: 0.2.6
Summary: A web gui for ROS (robot operating system)
Home-page: https://github.com/smanschi/ros_web_gui
Author: Simon Manschitz
Author-email: simon.manschitz@gmx.de
License: UNKNOWN
Platform: UNKNOWN
Classifier: Programming Language :: Python :: 3
Classifier: License :: OSI Approved :: MIT License
Classifier: Operating System :: OS Independent
Requires-Python: >=3.6
Requires-Dist: Flask (>=1.1.2)
Requires-Dist: PyYAML (>=5.3.1)
Requires-Dist: pydot (>=1.4.2)
Requires-Dist: rosdep (>=0.20.1)
